poetry_aws_plugin/__init__.py
poetry_aws_plugin/plugin.py
poetry_aws_plugin-0.1.12.dist-info/LICENSE
poetry_aws_plugin-0.1.12.dist-info/METADATA
poetry_aws_plugin-0.1.12.dist-info/WHEEL
poetry_aws_plugin-0.1.12.dist-info/entry_points.txt
poetry_aws_plugin-0.1.12.dist-info/RECORD
