Metadata-Version: 2.1
Name: poetry-aws-plugin
Version: 0.1.12
Summary: A poetry plugin to help with AWS CodeArtifact authorization automatically
Home-page: https://github.com/xiasongh/poetry-aws-plugin
License: MIT
Keywords: aws,codeartifact,poetry
Author: Song Huang
Author-email: xiasongh@gmail.com
Requires-Python: >=3.10,<4.0
Classifier: License :: OSI Approved :: MIT License
Classifier: Programming Language :: Python :: 3
Classifier: Programming Language :: Python :: 3.10
Classifier: Programming Language :: Python :: 3.11
Classifier: Programming Language :: Python :: 3.12
Requires-Dist: boto3 (>=1.34.71,<2.0.0)
Requires-Dist: poetry (>=1.7.0,<2.0.0)
Project-URL: Repository, https://github.com/xiasongh/poetry-aws-plugin
